aesoptparam/__init__.py
aesoptparam/example.py
aesoptparam/parameterized.py
aesoptparam/parameters.py
aesoptparam/serializer.py
aesoptparam/test/dummy_instance.json
aesoptparam/test/dummy_schema.json
aesoptparam/test/test_parameterized.py
aesoptparam/test/test_parameters.py
aesoptparam/test/test_units.py
aesoptparam/test/test_utils.py
aesoptparam/utils/__init__.py
aesoptparam/utils/html_repr.py
aesoptparam/utils/json_utils.py
aesoptparam/utils/unit_library.ini
aesoptparam/utils/units.py
aesoptparam-0.3.7.dist-info/licenses/LICENSE
aesoptparam-0.3.7.dist-info/METADATA
aesoptparam-0.3.7.dist-info/WHEEL
aesoptparam-0.3.7.dist-info/top_level.txt
aesoptparam-0.3.7.dist-info/RECORD
