Metadata-Version: 2.4
Name: aesoptparam
Version: 0.3.7
Author-email: Kenneth Loenbaek <kenloen@dtu.dk>
Maintainer-email: Kenneth Loenbaek <kenloen@dtu.dk>
Project-URL: Documentation, https://aesopt.pages.windenergy.dtu.dk/aesoptparam
Project-URL: DTU-Wind-Gitlab, https://gitlab.windenergy.dtu.dk/AESOpt/aesoptparam
Project-URL: Changelog, https://gitlab.windenergy.dtu.dk/AESOpt/aesoptparam/-/blob/main/CHANGELOG.md
License-File: LICENSE
Requires-Dist: param==2.3.0
Requires-Dist: numpy
Requires-Dist: scipy
Provides-Extra: test
Requires-Dist: pytest; extra == "test"
Requires-Dist: pytest-cov; extra == "test"
Requires-Dist: isort; extra == "test"
Requires-Dist: black; extra == "test"
Requires-Dist: jsonschema; extra == "test"
Provides-Extra: docs
Requires-Dist: sphinx; extra == "docs"
Requires-Dist: sphinx-design; extra == "docs"
Requires-Dist: sphinx_book_theme; extra == "docs"
Requires-Dist: myst-parser; extra == "docs"
Requires-Dist: sphinx_external_toc; extra == "docs"
Requires-Dist: sphinxcontrib.bibtex; extra == "docs"
Requires-Dist: myst-nb; extra == "docs"
Requires-Dist: markdown; extra == "docs"
Requires-Dist: jupytext; extra == "docs"
Requires-Dist: setuptools; extra == "docs"
Provides-Extra: all
Requires-Dist: aesoptparam[docs,test]; extra == "all"
Dynamic: license-file
